HISTORY.rst
LICENSE
MANIFEST.in
README.md
requirements.txt
setup.py
python_salesforce.egg-info/PKG-INFO
python_salesforce.egg-info/SOURCES.txt
python_salesforce.egg-info/dependency_links.txt
python_salesforce.egg-info/not-zip-safe
python_salesforce.egg-info/requires.txt
python_salesforce.egg-info/top_level.txt
scripts/sf-cli
scripts/sf-exchange-auth
sforce/__init__.py
sforce/auth.py
sforce/client.py
sforce/cmd.py
sforce/models.py
sforce/util.py