Metadata-Version: 1.0
Name: python-salesforce
Version: 0.2.0
Summary: Python Salesforce auth/authorization client.
Home-page: https://github.com/debugmonkey/python-salesforce
Author: Adam Stokes
Author-email: adam.stokes@ubuntu.com
License: Copyright (c) 2013 Adam Stokes <adam.stokes@ubuntu.com>
